cstats/__init__.py
cstats/cstats.py
cstats-0.2.1.dist-info/DESCRIPTION.rst
cstats-0.2.1.dist-info/METADATA
cstats-0.2.1.dist-info/RECORD
cstats-0.2.1.dist-info/WHEEL
cstats-0.2.1.dist-info/entry_points.txt
cstats-0.2.1.dist-info/metadata.json
cstats-0.2.1.dist-info/top_level.txt
