Metadata-Version: 2.0
Name: cstats
Version: 0.2.1
Summary: cstats generates information about your file directory.
Home-page: https://github.com/mijecu25/cstats
Author: Miguel Velez
Author-email: miguelvelez@mijecu25.com
License: MIT
Keywords: stats,tool,command line,file system
Platform: UNKNOWN
Classifier: Development Status :: 5 - Production/Stable
Classifier: License :: OSI Approved :: MIT License
Classifier: Programming Language :: Python :: 2.7
Requires-Dist: docopt (>=0.6.1)
